{
  "title": "Teacher Lesson Feedback",
  "pages": [
    {
      "name": "page1",
      "elements": [
        {
          "type": "html",
          "name": "heading_with_unit",
          "html": "<h1>{course_name}</h1><h2>Unit {unit_number}: {unit_name}</h2><h3>Lesson {lesson_number}: {lesson_name}</h3>",
          "visibleIf": "!!{unit_name}"
        },
        {
          "type": "html",
          "name": "heading_without_unit",
          "html": "<h1>{course_name}</h1><h2>Lesson {lesson_number}: {lesson_name}</h2>",
          "visibleIf": "!{unit_name}"
        },
        {
          "type": "rating",
          "name": "how_enjoyable_nps",
          "title": "How much did you enjoy teaching this lesson?",
          "isRequired": true,
          "rateMin": 0,
          "rateMax": 10,
          "minRateDescription": "Not at all enjoyable",
          "maxRateDescription": "Extremely enjoyable"
        },
        {
          "type": "comment",
          "name": "any_feedback_fr",
          "title": "Do you have any feedback on this lesson for the Code.org curriculum team?",
          "isRequired": false
        }
      ]
    }
  ],
  "published": true
}