{
  "key": "algebrab",
  "display_name": "Computer Science in Algebra: Course B",
  "category": "math",
  "is_featured": false,
  "assignable": false,
  "curriculum_type": null,
  "marketing_initiative": null,
  "grade_levels": "6,7,8",
  "header": null,
  "image": "https://images.code.org/7a8cd03dbe7d5f6e32c9d6aeb6d3b42e-CSinA1.png",
  "cs_topic": "programming",
  "school_subject": "math",
  "device_compatibility": "{\"computer\":\"ideal\",\"chromebook\":\"ideal\",\"tablet\":\"not_recommended\",\"mobile\":\"incompatible\",\"no_device\":\"incompatible\"}",
  "description": null,
  "professional_learning_program": null,
  "video": null,
  "published_date": null,
  "self_paced_pl_course_offering_id": null
}
