{
  "key": "setWidthEach",
  "name": "group.setWidthEach()",
  "category": "Groups",
  "category_key": "groups",
  "content": "Sets the width of the sprite placeholder rectangle for every sprite in the group.\r\n\r\nThe default width is 100.",
  "examples": [
    {
      "name": "",
      "description": "",
      "code": "```\nvar group = createGroup();\r\ngroup.add(createSprite(100, 200));\r\ngroup.add(createSprite(300, 200));\r\nfunction draw() {\r\n  background(\"white\");\r\n  drawSprites();\r\n  if (mouseDown(\"leftButton\")){\r\n    group.setWidthEach(20);\r\n  }\r\n  if (mouseDown(\"rightButton\")){\r\n    group.setWidthEach(100);\r\n  }  \r\n}\n```",
      "app": "",
      "image": null,
      "appDisplayType": "codeFromCodeField",
      "embedAppWithCodeHeight": 310
    }
  ],
  "palette_params": [
    {
      "name": "width",
      "type": "Number",
      "required": true,
      "description": "The width of the sprites in pixels."
    }
  ],
  "return_value": "No return value. Changes output in the display after drawSprites() is called.",
  "short_description": "Sets the width of the sprite placeholder rectangle for every sprite in the group.",
  "syntax": "setWidthEach(width)",
  "tips": "- use `group.setScaleEach` to resize a sprite and keep the height to width ratio constant.\r\n- Groups of sprites all have the same functions and you use the dot notation (combining the name of the group, followed by a dot, with the function name) to call the function for that group of sprites.\r\n- Any changes to the properties of a sprite will not be seen until after `drawSprites()` is called."
}