{
  "category_key": "org_code_media",
  "content": "",
  "examples": "[]",
  "external_documentation": "",
  "fields": "[{\"name\":\"NORMAL\",\"type\":\"int\",\"description\":\"Represents a “normal” style for a font. This text is an example of a normal font style.\\n\"},{\"name\":\"BOLD\",\"type\":\"int\",\"description\":\"Represents a bold style for a font, which has heavier lines.\\n\\n\\u003cp style=\\\"font-family: sans-serif; font-weight:bolder;\\\"\\u003eThis is some example bold text.\\u003c/p\\u003e\"},{\"name\":\"ITALIC\",\"type\":\"int\",\"description\":\"Represents an italic style for a font, which is slanted forward.\\n\\n\\u003cem\\u003eThis is some example italic text.\\u003c/em\\u003e\"},{\"name\":\"BOLD_ITALIC\",\"type\":\"int\",\"description\":\"Represents a bold and italic style for a font.\\n\\n\\u003cp style=\\\"font-family: sans-serif; font-weight: bolder; font-style: italic;\\\"\\u003eThis is an example of bold italic text.\\u003c/p\\u003e\"}]",
  "key": "FontStyle",
  "name": "FontStyle",
  "syntax": "",
  "tips": "",
  "methods": [

  ]
}